[
    {
        "key": "dbln",
        "value": "%7B%2261579695301935%22%3A%22D5XFxQ7E%22%7D",
        "domain": "facebook.com",
        "path": "/login/device-based/",
        "hostOnly": false,
        "creation": "2025-08-22T09:24:26.739Z",
        "lastAccessed": "2025-08-22T09:24:26.741Z"
    },
    {
        "key": "datr",
        "value": "gUunaAc-GPqK5NYgADSt3d3D",
        "domain": "facebook.com",
        "path": "/",
        "hostOnly": false,
        "creation": "2025-08-22T09:24:26.742Z",
        "lastAccessed": "2025-08-22T09:24:26.742Z"
    },
    {
        "key": "sb",
        "value": "gUunaPQ8TzAUNxKK4O5kkKfz",
        "domain": "facebook.com",
        "path": "/",
        "hostOnly": false,
        "creation": "2025-08-22T09:24:26.742Z",
        "lastAccessed": "2025-08-22T09:24:26.742Z"
    },
    {
        "key": "locale",
        "value": "en_GB",
        "domain": "facebook.com",
        "path": "/",
        "hostOnly": false,
        "creation": "2025-08-22T09:24:26.742Z",
        "lastAccessed": "2025-08-22T09:24:26.742Z"
    },
    {
        "key": "ps_l",
        "value": "1",
        "domain": "facebook.com",
        "path": "/",
        "hostOnly": false,
        "creation": "2025-08-22T09:24:26.742Z",
        "lastAccessed": "2025-08-22T09:24:26.742Z"
    },
    {
        "key": "ps_n",
        "value": "1",
        "domain": "facebook.com",
        "path": "/",
        "hostOnly": false,
        "creation": "2025-08-22T09:24:26.742Z",
        "lastAccessed": "2025-08-22T09:24:26.742Z"
    },
    {
        "key": "vpd",
        "value": "v1%3B766x412x1.75",
        "domain": "facebook.com",
        "path": "/",
        "hostOnly": false,
        "creation": "2025-08-22T09:24:26.742Z",
        "lastAccessed": "2025-08-22T09:24:26.742Z"
    },
    {
        "key": "pas",
        "value": "61579695301935%3A34EsM1sBhD%2C61579484288124%3ACsI3sKD1Ik",
        "domain": "facebook.com",
        "path": "/",
        "hostOnly": false,
        "creation": "2025-08-22T09:24:26.742Z",
        "lastAccessed": "2025-08-22T09:24:26.742Z"
    },
    {
        "key": "m_pixel_ratio",
        "value": "1.75",
        "domain": "facebook.com",
        "path": "/",
        "hostOnly": false,
        "creation": "2025-08-22T09:24:26.742Z",
        "lastAccessed": "2025-08-22T09:24:26.742Z"
    },
    {
        "key": "wd",
        "value": "412x869",
        "domain": "facebook.com",
        "path": "/",
        "hostOnly": false,
        "creation": "2025-08-22T09:24:26.742Z",
        "lastAccessed": "2025-08-22T09:24:26.742Z"
    },
    {
        "key": "c_user",
        "value": "61579695301935",
        "domain": "facebook.com",
        "path": "/",
        "hostOnly": false,
        "creation": "2025-08-22T09:24:26.742Z",
        "lastAccessed": "2025-08-22T09:24:26.742Z"
    },
    {
        "key": "xs",
        "value": "19%3Aj5ERhen62HPHwQ%3A2%3A1755854629%3A-1%3A-1",
        "domain": "facebook.com",
        "path": "/",
        "hostOnly": false,
        "creation": "2025-08-22T09:24:26.742Z",
        "lastAccessed": "2025-08-22T09:24:26.742Z"
    },
    {
        "key": "fr",
        "value": "0lwb98t8YAJ9fQhu4.AWfJDcEGST4YmeLMmM4CuKkU8pUeVrMTjlb-vFOY9HUyQEB95TY.Bop0uB..AAA.0.0.BoqDcn.AWe2n_LEfrsdzBXNLLapHRE-cx8",
        "domain": "facebook.com",
        "path": "/",
        "hostOnly": false,
        "creation": "2025-08-22T09:24:26.742Z",
        "lastAccessed": "2025-08-22T09:24:26.742Z"
    },
    {
        "key": "fbl_st",
        "value": "101216132%3BT%3A29264243",
        "domain": "facebook.com",
        "path": "/",
        "hostOnly": false,
        "creation": "2025-08-22T09:24:26.742Z",
        "lastAccessed": "2025-08-22T09:24:26.742Z"
    },
    {
        "key": "wl_cbv",
        "value": "v2%3Bclient_version%3A2899%3Btimestamp%3A1755854631",
        "domain": "facebook.com",
        "path": "/",
        "hostOnly": false,
        "creation": "2025-08-22T09:24:26.742Z",
        "lastAccessed": "2025-08-22T09:24:26.742Z"
    }
        ]
